niah-1.0.0.data/scripts/niah
niah-1.0.0.dist-info/DESCRIPTION.rst
niah-1.0.0.dist-info/METADATA
niah-1.0.0.dist-info/RECORD
niah-1.0.0.dist-info/WHEEL
niah-1.0.0.dist-info/metadata.json
niah-1.0.0.dist-info/top_level.txt
src/__init__.py
