Metadata-Version: 2.0
Name: niah
Version: 1.0.0
Summary: Find the open source vulnerabilities to get more details niahsecurity.io
Home-page: http://packages.python.org/niahsecurity
Author: Niah Technologies Inc
Author-email: o-admin@niahsecurity.io
License: MIT
Keywords: vulnerability scanner,sca software composition analysis
Platform: UNKNOWN
Classifier: Programming Language :: Python :: 3.7
Classifier: License :: OSI Approved :: MIT License
Classifier: Operating System :: OS Independent
Requires-Dist: PyGithub
Requires-Dist: docker (==4.4.1)
Requires-Dist: glob2
Requires-Dist: pexpect
Requires-Dist: prettytable
Requires-Dist: ptyprocess
Requires-Dist: pyfiglet
Requires-Dist: requests
Requires-Dist: semantic-version
Requires-Dist: setuptools (==44.1.1)
Requires-Dist: termcolor
Requires-Dist: tqdm
